riverpod_3_scanner/__init__.py
riverpod_3_scanner/__main__.py
riverpod_3_scanner/scanner.py
riverpod_3_scanner-1.3.1.dist-info/licenses/AUTHORS
riverpod_3_scanner-1.3.1.dist-info/licenses/LICENSE
riverpod_3_scanner-1.3.1.dist-info/METADATA
riverpod_3_scanner-1.3.1.dist-info/WHEEL
riverpod_3_scanner-1.3.1.dist-info/entry_points.txt
riverpod_3_scanner-1.3.1.dist-info/top_level.txt
riverpod_3_scanner-1.3.1.dist-info/RECORD
