Metadata-Version: 2.4
Name: riverpod-3-scanner
Version: 1.3.1
Summary: Comprehensive static analysis tool for detecting Riverpod 3.0 async safety violations in Flutter/Dart projects
Home-page: https://github.com/DayLight-Creative-Technologies/riverpod_3_scanner
Author: Steven Day
Author-email: Steven Day <support@daylightcreative.tech>
Maintainer-email: Steven Day <support@daylightcreative.tech>
License: MIT License
Project-URL: Homepage, https://github.com/DayLight-Creative-Technologies/riverpod_3_scanner
Project-URL: Documentation, https://github.com/DayLight-Creative-Technologies/riverpod_3_scanner/blob/main/docs/GUIDE.md
Project-URL: Repository, https://github.com/DayLight-Creative-Technologies/riverpod_3_scanner
Project-URL: Issues, https://github.com/DayLight-Creative-Technologies/riverpod_3_scanner/issues
Project-URL: Changelog, https://github.com/DayLight-Creative-Technologies/riverpod_3_scanner/blob/main/CHANGELOG.md
Keywords: riverpod,flutter,dart,static-analysis,linter,code-quality,async-safety,riverpod-3,safety-checker
Classifier: Development Status :: 5 - Production/Stable
Classifier: Intended Audience :: Developers
Classifier: Topic :: Software Development :: Quality Assurance
Classifier: Topic :: Software Development :: Testing
Classifier: License :: OSI Approved :: MIT License
Classifier: Programming Language :: Python :: 3
Classifier: Programming Language :: Python :: 3.7
Classifier: Programming Language :: Python :: 3.8
Classifier: Programming Language :: Python :: 3.9
Classifier: Programming Language :: Python :: 3.10
Classifier: Programming Language :: Python :: 3.11
Classifier: Programming Language :: Python :: 3.12
Classifier: Operating System :: OS Independent
Classifier: Environment :: Console
Requires-Python: >=3.7
License-File: LICENSE
License-File: AUTHORS
Dynamic: author
Dynamic: home-page
Dynamic: license-file
Dynamic: requires-python
